simple_plugin_loader/__init__.py
simple_plugin_loader/loader.py
simple_plugin_loader/py.typed
simple_plugin_loader/sample_plugin.py
simple_plugin_loader-3.0.0.dist-info/LICENSE
simple_plugin_loader-3.0.0.dist-info/METADATA
simple_plugin_loader-3.0.0.dist-info/WHEEL
simple_plugin_loader-3.0.0.dist-info/RECORD
