Metadata-Version: 2.1
Name: simple-plugin-loader
Version: 3.0.0
Summary: Dynamically load other python modules to your project.
Home-page: https://github.com/mammo0/py-simple-plugin-loader
License: GPL-3.0-only
Author: Marc Ammon
Author-email: marc.ammon@hotmail.de
Requires-Python: >=3.8
Classifier: License :: OSI Approved :: GNU General Public License v3 (GPLv3)
Classifier: Operating System :: OS Independent
Classifier: Programming Language :: Python :: 3
Classifier: Programming Language :: Python :: 3.8
Classifier: Programming Language :: Python :: 3.9
Classifier: Programming Language :: Python :: 3.10
Classifier: Programming Language :: Python :: 3.11
Requires-Dist: simple-classproperty (>=3.0)
